odoo9_addon_sale_operating_unit-9.0.1.0.0.99.dev2-py2.7-nspkg.pth
odoo9_addon_sale_operating_unit-9.0.1.0.0.99.dev2.dist-info/METADATA
odoo9_addon_sale_operating_unit-9.0.1.0.0.99.dev2.dist-info/RECORD
odoo9_addon_sale_operating_unit-9.0.1.0.0.99.dev2.dist-info/WHEEL
odoo9_addon_sale_operating_unit-9.0.1.0.0.99.dev2.dist-info/namespace_packages.txt
odoo9_addon_sale_operating_unit-9.0.1.0.0.99.dev2.dist-info/top_level.txt
odoo_addons/sale_operating_unit/README.rst
odoo_addons/sale_operating_unit/__init__.py
odoo_addons/sale_operating_unit/__openerp__.py
odoo_addons/sale_operating_unit/models/__init__.py
odoo_addons/sale_operating_unit/models/sale.py
odoo_addons/sale_operating_unit/report/__init__.py
odoo_addons/sale_operating_unit/report/sale_report.py
odoo_addons/sale_operating_unit/security/sale_security.xml
odoo_addons/sale_operating_unit/static/description/icon.png
odoo_addons/sale_operating_unit/tests/__init__.py
odoo_addons/sale_operating_unit/tests/test_sale_operating_unit.py
odoo_addons/sale_operating_unit/views/sale_report_view.xml
odoo_addons/sale_operating_unit/views/sale_view.xml
